trainloop_evals/__init__.py
trainloop_evals/config.py
trainloop_evals/exporter.py
trainloop_evals/instrumentation/__init__.py
trainloop_evals/instrumentation/http_client_lib.py
trainloop_evals/instrumentation/httpx_lib.py
trainloop_evals/instrumentation/requests_lib.py
trainloop_evals/instrumentation/utils.py
trainloop_evals/logger.py
trainloop_evals/register.py
trainloop_evals/store.py
trainloop_evals/types.py
trainloop_evals_sdk-0.4.0.dist-info/METADATA
trainloop_evals_sdk-0.4.0.dist-info/WHEEL
trainloop_evals_sdk-0.4.0.dist-info/RECORD
