Metadata-Version: 2.3
Name: trainloop-evals-sdk
Version: 0.4.0
Summary: TrainLoop Evaluations SDK for data collection and evaluation
Author: Mason Pierce
Author-email: masonpierce@trainloop.ai
Requires-Python: >=3.9,<4.0
Classifier: Programming Language :: Python :: 3
Classifier: Programming Language :: Python :: 3.9
Classifier: Programming Language :: Python :: 3.10
Classifier: Programming Language :: Python :: 3.11
Classifier: Programming Language :: Python :: 3.12
Classifier: Programming Language :: Python :: 3.13
Requires-Dist: pyyaml (>=6.0,<7.0)
Requires-Dist: requests (>=2.31.0,<3.0.0)
